{
    "$schema": "https://json-schema.org/draft/2020-12/schema",
    "$id": "https://php-edifact.github.io/edifact-schema/D12A/compositedataelement/C270.edifact.schema.json",
    "title": "C270",
    "description": "Control total for checking integrity of a message or part of a message.",
    "type": "object",
    "properties": {
        "controlTotalTypeCodeQualifier": {
            "$ref": "https://php-edifact.github.io/edifact-schema/D12A/dataelement/6069.edifact.schema.json"
        },
        "controlTotalQuantity": {
            "$ref": "https://php-edifact.github.io/edifact-schema/D12A/dataelement/6066.edifact.schema.json"
        },
        "measurementUnitCode": {
            "$ref": "https://php-edifact.github.io/edifact-schema/D12A/dataelement/6411.edifact.schema.json"
        }
    },
    "required": []
}