{
    "$schema": "https://json-schema.org/draft/2020-12/schema",
    "$id": "https://php-edifact.github.io/edifact-schema/D99A/compositedataelement/C059.edifact.schema.json",
    "title": "C059",
    "description": "Street address and/or PO Box number in a structured address: one to four lines.",
    "type": "object",
    "properties": {
        "streetAndNumberOrp.o.Box": {
            "$ref": "https://php-edifact.github.io/edifact-schema/D99A/dataelement/3042.edifact.schema.json"
        },
        "streetAndNumberOrp.o.Box2": {
            "$ref": "https://php-edifact.github.io/edifact-schema/D99A/dataelement/3042.edifact.schema.json"
        },
        "streetAndNumberOrp.o.Box3": {
            "$ref": "https://php-edifact.github.io/edifact-schema/D99A/dataelement/3042.edifact.schema.json"
        },
        "streetAndNumberOrp.o.Box4": {
            "$ref": "https://php-edifact.github.io/edifact-schema/D99A/dataelement/3042.edifact.schema.json"
        }
    },
    "required": []
}